[
  {
    "record_id": "TR104011150304001",
    "status": "draft",
    "form_type": "travel",
    "form_date": "2026-03-03T16:00:00.000Z",
    "employee_name": "方澤沛",
    "employee_no": 10401,
    "department": "化安處",
    "plan_code": "115CA011/化學品計畫",
    "trip_purpose": "0305，OSHA 定量暴評教學_高雄場",
    "from_location": "台中",
    "to_location": "高雄",
    "trip_date_start": "2026-03-04T16:00:00.000Z",
    "trip_time_start": "",
    "trip_date_end": "2026-03-04T16:00:00.000Z",
    "trip_time_end": "",
    "trip_days": 1,
    "transport_tools": "[\"高鐵\",\"其他\"]",
    "transportation_type": "高鐵,其他",
    "gov_car_no": "",
    "private_car_km": 0,
    "private_car_no": "",
    "other_transport_desc": "台鐵",
    "estimated_cost": 0,
    "expense_rows": "[{\"日期\":\"2026-03-05\",\"起訖地點\":\"\",\"車別\":\"高鐵\",\"交通費\":0,\"膳雜費\":0,\"住宿費\":0,\"其它\":0,\"單據編號\":\"\"},{\"日期\":\"\",\"起訖地點\":\"\",\"車別\":\"台鐵\",\"交通費\":0,\"膳雜費\":0,\"住宿費\":0,\"其它\":0,\"單據編號\":\"\"},{\"日期\":\"\",\"起訖地點\":\"\",\"車別\":\"\",\"交通費\":0,\"膳雜費\":0,\"住宿費\":0,\"其它\":0,\"單據編號\":\"\"}]",
    "amount_total": 0,
    "amount_total_upper": 0,
    "attachments": "[]",
    "signature_file": "{}",
    "handler_name": "方澤沛",
    "project_manager_name": "",
    "department_manager_name": "",
    "accountant_name": "",
    "note_public": "",
    "remarks_internal": "",
    "send_pdf_to_email": false,
    "budget_source": "",
    "owner_name": "方澤沛",
    "user_email": "pbpk@sahtech.org",
    "actor_role": "user",
    "source_system": "travel",
    "created_at": "2026-03-16T11:26:36.000Z",
    "created_by": "pbpk@sahtech.org",
    "updated_at": "2026-03-16T11:26:36.000Z",
    "updated_by": "pbpk@sahtech.org",
    "submitted_at": "",
    "submitted_by": "",
    "is_deleted": "",
    "deleted_at": "",
    "deleted_by": "",
    "version": "",
    "last_event_id": "",
    "last_synced_at": "",
    "deleted_reason": "",
    "_row_number": 4,
    "_sheet_name": "草稿列表"
  },
  {
    "record_id": "TR104011150224001",
    "status": "draft",
    "form_type": "travel",
    "form_date": "2026-02-23T16:00:00.000Z",
    "employee_name": "方澤沛",
    "employee_no": 10401,
    "department": "化安處",
    "plan_code": "115GO005/指定菸品計畫",
    "trip_purpose": "工作會議，菸品首次申報討論",
    "from_location": "",
    "to_location": "台中",
    "trip_date_start": "2026-02-23T16:00:00.000Z",
    "trip_time_start": "",
    "trip_date_end": "2026-02-23T16:00:00.000Z",
    "trip_time_end": "",
    "trip_days": 1,
    "transport_tools": "[\"計程車\",\"高鐵\"]",
    "transportation_type": "計程車,高鐵",
    "gov_car_no": "",
    "private_car_km": 0,
    "private_car_no": "",
    "other_transport_desc": "",
    "estimated_cost": 0,
    "expense_rows": "[{\"日期\":\"2026-02-25\",\"起訖地點\":\"\",\"車別\":\"高鐵\",\"交通費\":0,\"膳雜費\":0,\"住宿費\":0,\"其它\":0,\"單據編號\":\"\"},{\"日期\":\"\",\"起訖地點\":\"\",\"車別\":\"計程車\",\"交通費\":0,\"膳雜費\":0,\"住宿費\":0,\"其它\":0,\"單據編號\":\"\"},{\"日期\":\"\",\"起訖地點\":\"\",\"車別\":\"\",\"交通費\":0,\"膳雜費\":0,\"住宿費\":0,\"其它\":0,\"單據編號\":\"\"}]",
    "amount_total": 0,
    "amount_total_upper": 0,
    "attachments": "[]",
    "signature_file": "{}",
    "handler_name": "方澤沛",
    "project_manager_name": "",
    "department_manager_name": "",
    "accountant_name": "",
    "note_public": "",
    "remarks_internal": "",
    "send_pdf_to_email": false,
    "budget_source": "",
    "owner_name": "方澤沛",
    "user_email": "pbpk@sahtech.org",
    "actor_role": "user",
    "source_system": "travel",
    "created_at": "2026-03-16T11:24:40.000Z",
    "created_by": "pbpk@sahtech.org",
    "updated_at": "2026-03-16T11:24:40.000Z",
    "updated_by": "pbpk@sahtech.org",
    "submitted_at": "",
    "submitted_by": "",
    "is_deleted": "",
    "deleted_at": "",
    "deleted_by": "",
    "version": "",
    "last_event_id": "",
    "last_synced_at": "",
    "deleted_reason": "",
    "_row_number": 3,
    "_sheet_name": "草稿列表"
  },
  {
    "record_id": "TR960061150316002",
    "status": "draft",
    "form_type": "travel",
    "form_date": "2026-03-15T16:00:00.000Z",
    "employee_name": "李政憲",
    "employee_no": 96006,
    "department": "化安處",
    "plan_code": "115CA006/致癌計畫",
    "trip_purpose": "DomesticTrip_Draft",
    "from_location": "",
    "to_location": "",
    "trip_date_start": "2026-03-15T16:00:00.000Z",
    "trip_time_start": "",
    "trip_date_end": "2026-03-15T16:00:00.000Z",
    "trip_time_end": "",
    "trip_days": 1,
    "transport_tools": "[]",
    "transportation_type": "",
    "gov_car_no": "",
    "private_car_km": 0,
    "private_car_no": "",
    "other_transport_desc": "",
    "estimated_cost": 0,
    "expense_rows": "[{\"日期\":\"2026-03-16\",\"起訖地點\":\"\",\"車別\":\"\",\"交通費\":0,\"膳雜費\":0,\"住宿費\":0,\"其它\":0,\"單據編號\":\"\"}]",
    "amount_total": "2026-03-15T16:00:00.000Z",
    "amount_total_upper": "",
    "attachments": "",
    "signature_file": 0,
    "handler_name": 0,
    "project_manager_name": 0,
    "department_manager_name": 0,
    "accountant_name": "",
    "note_public": 0,
    "remarks_internal": 0,
    "send_pdf_to_email": "[]",
    "budget_source": "{}",
    "owner_name": "李政憲",
    "user_email": "",
    "actor_role": "",
    "source_system": "",
    "created_at": "",
    "created_by": "",
    "updated_at": false,
    "updated_by": "",
    "submitted_at": "李政憲",
    "submitted_by": "",
    "is_deleted": false,
    "deleted_at": "",
    "deleted_by": "",
    "version": 1,
    "last_event_id": "61c629684e91429cafd4c95ea66da7b8",
    "last_synced_at": "2026-03-16T12:22:20.000Z",
    "deleted_reason": "",
    "_row_number": 5,
    "_sheet_name": "草稿列表"
  }
]